pdum/__init__.py
pdum/hydra/__init__.py
pdum/hydra/dynamic.py
pdum/hydra/py.typed
habemus_papadum_hydra-0.3.0.dist-info/METADATA
habemus_papadum_hydra-0.3.0.dist-info/WHEEL
habemus_papadum_hydra-0.3.0.dist-info/licenses/LICENSE
habemus_papadum_hydra-0.3.0.dist-info/RECORD
