Metadata-Version: 2.4
Name: habemus-papadum-hydra
Version: 0.3.0
Summary: Hydra utils
Project-URL: Homepage, https://github.com/habemus-papadum/pdum_hydra
Project-URL: Repository, https://github.com/habemus-papadum/pdum_hydra
Project-URL: Documentation, https://github.com/habemus-papadum/pdum_hydra
Author-email: Nehal Patel <nehal@alum.mit.edu>
License: MIT License
License-File: LICENSE
Classifier: Intended Audience :: Developers
Classifier: License :: OSI Approved :: MIT License
Classifier: Operating System :: OS Independent
Classifier: Programming Language :: Python :: 3
Classifier: Topic :: Software Development :: Libraries
Classifier: Topic :: Software Development :: Libraries :: Python Modules
Requires-Python: >=3.12
Requires-Dist: hydra-core>=1.3.2
Requires-Dist: omegaconf>=2.3.0
